LICENSE
README.md
pyproject.toml
setup.py
mwrogue/__init__.py
mwrogue/auth_credentials.py
mwrogue/errors.py
mwrogue/esports_client.py
mwrogue/lookup_cache.py
mwrogue/template_modifier.py
mwrogue/wiki_time.py
mwrogue/wiki_time_parser.py
mwrogue.egg-info/PKG-INFO
mwrogue.egg-info/SOURCES.txt
mwrogue.egg-info/dependency_links.txt
mwrogue.egg-info/requires.txt
mwrogue.egg-info/top_level.txt
mwrogue/error_reporting/__init__.py
mwrogue/error_reporting/wiki_content_error.py
mwrogue/error_reporting/wiki_error.py
mwrogue/error_reporting/wiki_script_error.py