Metadata-Version: 2.1
Name: mwrogue
Version: 0.1.2
Summary: Client for accessing Fandom/Gamepedia Esports Wikis
Home-page: https://github.com/RheingoldRiver/mwrogue
Author: RheingoldRiver
Author-email: river.esports@gmail.com
License: UNKNOWN
Platform: UNKNOWN
Requires-Python: >=3.6
License-File: LICENSE
